{"keyvault":"fail","keyvault_error":"(Forbidden) Caller is not authorized to perform action on resource.\r\nIf role assignments, deny assignments or role definitions were changed recently, please observe propagation time.\r\nCaller: appid=b2","servicebus":"success","storage":"fail","storage_error":"This request is not authorized to perform this operation using this permission.\nRequestId:77e3f3b7-d01e-0062-48d7-c9c84c000000\nTime:2026-04-11T17:19:17.3781590Z\nErrorCode:AuthorizationPermissionMismat","timestamp_utc":"2026-04-11T17:19:17.032907+00:00"}
